Metadata-Version: 1.1
Name: pyFart
Version: 0.0.1
Summary: prints a funny line to the console
Home-page: UNKNOWN
Author: Brendan Corcoran
Author-email: brendan.j.corcoran@gmail.com
License: UNKNOWN
Keywords: python,fart
Platform: UNKNOWN
Classifier: Development Status :: 3 - Alpha
Classifier: Intended Audience :: Education
Classifier: Programming Language :: Python :: 2
Classifier: Programming Language :: Python :: 3
Classifier: Operating System :: MacOS :: MacOS X
Classifier: Operating System :: Microsoft :: Windows
